<?xml version="1.0" encoding="utf-8"?>
<odoo>
    <!-- List View -->
    <record id="sale_order_segment_view_tree" model="ir.ui.view">
        <field name="name">sale.order.segment.tree</field>
        <field name="model">sale.order.segment</field>
        <field name="arch" type="xml">
            <list decoration-primary="level == 1"
                  decoration-info="level == 2"
                  decoration-muted="level == 3"
                  decoration-warning="level == 4">
                <field name="sequence" widget="handle"/>
                <field name="name"/>
                <field name="full_path"/>
                <field name="child_count"/>
                <field name="product_count" string="Products"/>
                <field name="subtotal" sum="Subtotal"/>
                <field name="total" sum="Total"/>
                <field name="level" column_invisible="1"/>
            </list>
        </field>
    </record>

    <!-- Form View -->
    <record id="sale_order_segment_view_form" model="ir.ui.view">
        <field name="name">sale.order.segment.form</field>
        <field name="model">sale.order.segment</field>
        <field name="arch" type="xml">
            <form string="Segment">
                <sheet>
                    <div class="oe_button_box" name="button_box">
                        <button name="action_view_children"
                                type="object"
                                class="oe_stat_button"
                                icon="fa-sitemap"
                                invisible="child_count == 0">
                            <div class="o_stat_info">
                                <span class="o_stat_value">
                                    <field name="child_count"/>
                                </span>
                                <span class="o_stat_text">Sub-segmentos</span>
                            </div>
                            <div class="o_stat_info" invisible="child_depth == 0">
                                <span class="o_stat_text">
                                    (<field name="child_depth" readonly="1"/> niveles)
                                </span>
                            </div>
                        </button>
                    </div>
                    <group>
                        <group>
                            <field name="name"/>
                            <field name="parent_id" domain="[('order_id', '=', order_id)]"/>
                            <field name="order_id"/>
                        </group>
                        <group>
                            <field name="sequence"/>
                            <field name="level" readonly="1"/>
                            <field name="full_path" readonly="1"/>
                            <field name="currency_id" invisible="1"/>
                            <field name="subtotal" readonly="1"/>
                            <field name="total" readonly="1"/>
                        </group>
                    </group>
                    <notebook>
                        <page string="Description" name="description">
                            <field name="description"/>
                        </page>
                        <page string="Order Lines" name="order_lines">
                            <field name="line_ids">
                                <list>
                                    <field name="product_id"/>
                                    <field name="product_uom_qty"/>
                                    <field name="price_unit"/>
                                    <field name="price_subtotal"/>
                                </list>
                            </field>
                        </page>
                        <page string="Sub-segments" name="children">
                            <field name="child_ids">
                                <list>
                                    <field name="sequence" widget="handle"/>
                                    <field name="name"/>
                                    <field name="level"/>
                                </list>
                            </field>
                        </page>
                    </notebook>
                </sheet>
            </form>
        </field>
    </record>

    <!-- Search View -->
    <record id="sale_order_segment_view_search" model="ir.ui.view">
        <field name="name">sale.order.segment.search</field>
        <field name="model">sale.order.segment</field>
        <field name="arch" type="xml">
            <search string="Segments">
                <field name="name"/>
                <field name="parent_id"/>
                <filter string="Root Segments" name="root"
                        domain="[('parent_id', '=', False)]"/>
                <group expand="0" string="Group By">
                    <filter string="Parent" name="group_parent"
                            context="{'group_by': 'parent_id'}"/>
                    <filter string="Level" name="group_level"
                            context="{'group_by': 'level'}"/>
                </group>
            </search>
        </field>
    </record>

    <!-- Action -->
    <record id="sale_order_segment_action" model="ir.actions.act_window">
        <field name="name">Segments</field>
        <field name="res_model">sale.order.segment</field>
        <field name="view_mode">list,form</field>
        <field name="search_view_id" ref="sale_order_segment_view_search"/>
        <field name="context">{'search_default_root': 1}</field>
    </record>

</odoo>
